<?xml version="1.0" encoding="UTF-8"?>
<!DOCTYPE mapper PUBLIC "-//mybatis.org//DTD Mapper 3.0//EN" "http://mybatis.org/dtd/mybatis-3-mapper.dtd">
<mapper namespace="com.uxiaoxi.ym.appserver.db.cluster.mapper.RemarkMapper">
  <resultMap id="BaseResultMap" type="com.uxiaoxi.ym.appserver.db.cluster.dto.Remark">
    <!--
      WARNING - @mbggenerated
      This element is automatically generated by MyBatis Generator, do not modify.
      This element was generated on Sat Jan 30 18:31:14 CST 2016.
    -->
    <id column="id" jdbcType="BIGINT" property="id" />
    <result column="acc_id" jdbcType="BIGINT" property="accId" />
    <result column="acc_id_obj" jdbcType="BIGINT" property="accIdObj" />
    <result column="clu_id" jdbcType="BIGINT" property="cluId" />
    <result column="remark" jdbcType="VARCHAR" property="remark" />
    <result column="create_dt" jdbcType="TIMESTAMP" property="createDt" />
  </resultMap>
  <sql id="Example_Where_Clause">
    <!--
      WARNING - @mbggenerated
      This element is automatically generated by MyBatis Generator, do not modify.
      This element was generated on Sat Jan 30 18:31:14 CST 2016.
    -->
    <where>
      <foreach collection="oredCriteria" item="criteria" separator="or">
        <if test="criteria.valid">
          <trim prefix="(" prefixOverrides="and" suffix=")">
            <foreach collection="criteria.criteria" item="criterion">
              <choose>
                <when test="criterion.noValue">
                  and ${criterion.condition}
                </when>
                <when test="criterion.singleValue">
                  and ${criterion.condition} #{criterion.value}
                </when>
                <when test="criterion.betweenValue">
                  and ${criterion.condition} #{criterion.value} and #{criterion.secondValue}
                </when>
                <when test="criterion.listValue">
                  and ${criterion.condition}
                  <foreach close=")" collection="criterion.value" item="listItem" open="(" separator=",">
                    #{listItem}
                  </foreach>
                </when>
              </choose>
            </foreach>
          </trim>
        </if>
      </foreach>
    </where>
  </sql>
  <sql id="Update_By_Example_Where_Clause">
    <!--
      WARNING - @mbggenerated
      This element is automatically generated by MyBatis Generator, do not modify.
      This element was generated on Sat Jan 30 18:31:14 CST 2016.
    -->
    <where>
      <foreach collection="example.oredCriteria" item="criteria" separator="or">
        <if test="criteria.valid">
          <trim prefix="(" prefixOverrides="and" suffix=")">
            <foreach collection="criteria.criteria" item="criterion">
              <choose>
                <when test="criterion.noValue">
                  and ${criterion.condition}
                </when>
                <when test="criterion.singleValue">
                  and ${criterion.condition} #{criterion.value}
                </when>
                <when test="criterion.betweenValue">
                  and ${criterion.condition} #{criterion.value} and #{criterion.secondValue}
                </when>
                <when test="criterion.listValue">
                  and ${criterion.condition}
                  <foreach close=")" collection="criterion.value" item="listItem" open="(" separator=",">
                    #{listItem}
                  </foreach>
                </when>
              </choose>
            </foreach>
          </trim>
        </if>
      </foreach>
    </where>
  </sql>
  <sql id="Base_Column_List">
    <!--
      WARNING - @mbggenerated
      This element is automatically generated by MyBatis Generator, do not modify.
      This element was generated on Sat Jan 30 18:31:14 CST 2016.
    -->
    id, acc_id, acc_id_obj, clu_id, remark, create_dt
  </sql>
  <select id="selectByExample" parameterType="com.uxiaoxi.ym.appserver.db.cluster.dto.RemarkExample" resultMap="BaseResultMap">
    <!--
      WARNING - @mbggenerated
      This element is automatically generated by MyBatis Generator, do not modify.
      This element was generated on Sat Jan 30 18:31:14 CST 2016.
    -->
    select
    <if test="distinct">
      distinct
    </if>
    <include refid="Base_Column_List" />
    from remark
    <if test="_parameter != null">
      <include refid="Example_Where_Clause" />
    </if>
    <if test="orderByClause != null">
      order by ${orderByClause}
    </if>
  </select>
  <select id="selectByPrimaryKey" parameterType="java.lang.Long" resultMap="BaseResultMap">
    <!--
      WARNING - @mbggenerated
      This element is automatically generated by MyBatis Generator, do not modify.
      This element was generated on Sat Jan 30 18:31:14 CST 2016.
    -->
    select 
    <include refid="Base_Column_List" />
    from remark
    where id = #{id,jdbcType=BIGINT}
  </select>
  <delete id="deleteByPrimaryKey" parameterType="java.lang.Long">
    <!--
      WARNING - @mbggenerated
      This element is automatically generated by MyBatis Generator, do not modify.
      This element was generated on Sat Jan 30 18:31:14 CST 2016.
    -->
    delete from remark
    where id = #{id,jdbcType=BIGINT}
  </delete>
  <delete id="deleteByExample" parameterType="com.uxiaoxi.ym.appserver.db.cluster.dto.RemarkExample">
    <!--
      WARNING - @mbggenerated
      This element is automatically generated by MyBatis Generator, do not modify.
      This element was generated on Sat Jan 30 18:31:14 CST 2016.
    -->
    delete from remark
    <if test="_parameter != null">
      <include refid="Example_Where_Clause" />
    </if>
  </delete>
  <insert id="insert" parameterType="com.uxiaoxi.ym.appserver.db.cluster.dto.Remark">
    <!--
      WARNING - @mbggenerated
      This element is automatically generated by MyBatis Generator, do not modify.
      This element was generated on Sat Jan 30 18:31:14 CST 2016.
    -->
    <selectKey keyProperty="id" order="AFTER" resultType="java.lang.Long">
      SELECT LAST_INSERT_ID()
    </selectKey>
    insert into remark (acc_id, acc_id_obj, clu_id, 
      remark, create_dt)
    values (#{accId,jdbcType=BIGINT}, #{accIdObj,jdbcType=BIGINT}, #{cluId,jdbcType=BIGINT}, 
      #{remark,jdbcType=VARCHAR}, #{createDt,jdbcType=TIMESTAMP})
  </insert>
  <insert id="insertSelective" parameterType="com.uxiaoxi.ym.appserver.db.cluster.dto.Remark">
    <!--
      WARNING - @mbggenerated
      This element is automatically generated by MyBatis Generator, do not modify.
      This element was generated on Sat Jan 30 18:31:14 CST 2016.
    -->
    <selectKey keyProperty="id" order="AFTER" resultType="java.lang.Long">
      SELECT LAST_INSERT_ID()
    </selectKey>
    insert into remark
    <trim prefix="(" suffix=")" suffixOverrides=",">
      <if test="accId != null">
        acc_id,
      </if>
      <if test="accIdObj != null">
        acc_id_obj,
      </if>
      <if test="cluId != null">
        clu_id,
      </if>
      <if test="remark != null">
        remark,
      </if>
      <if test="createDt != null">
        create_dt,
      </if>
    </trim>
    <trim prefix="values (" suffix=")" suffixOverrides=",">
      <if test="accId != null">
        #{accId,jdbcType=BIGINT},
      </if>
      <if test="accIdObj != null">
        #{accIdObj,jdbcType=BIGINT},
      </if>
      <if test="cluId != null">
        #{cluId,jdbcType=BIGINT},
      </if>
      <if test="remark != null">
        #{remark,jdbcType=VARCHAR},
      </if>
      <if test="createDt != null">
        #{createDt,jdbcType=TIMESTAMP},
      </if>
    </trim>
  </insert>
  <select id="countByExample" parameterType="com.uxiaoxi.ym.appserver.db.cluster.dto.RemarkExample" resultType="java.lang.Integer">
    <!--
      WARNING - @mbggenerated
      This element is automatically generated by MyBatis Generator, do not modify.
      This element was generated on Sat Jan 30 18:31:14 CST 2016.
    -->
    select count(*) from remark
    <if test="_parameter != null">
      <include refid="Example_Where_Clause" />
    </if>
  </select>
  <update id="updateByExampleSelective" parameterType="map">
    <!--
      WARNING - @mbggenerated
      This element is automatically generated by MyBatis Generator, do not modify.
      This element was generated on Sat Jan 30 18:31:14 CST 2016.
    -->
    update remark
    <set>
      <if test="record.id != null">
        id = #{record.id,jdbcType=BIGINT},
      </if>
      <if test="record.accId != null">
        acc_id = #{record.accId,jdbcType=BIGINT},
      </if>
      <if test="record.accIdObj != null">
        acc_id_obj = #{record.accIdObj,jdbcType=BIGINT},
      </if>
      <if test="record.cluId != null">
        clu_id = #{record.cluId,jdbcType=BIGINT},
      </if>
      <if test="record.remark != null">
        remark = #{record.remark,jdbcType=VARCHAR},
      </if>
      <if test="record.createDt != null">
        create_dt = #{record.createDt,jdbcType=TIMESTAMP},
      </if>
    </set>
    <if test="_parameter != null">
      <include refid="Update_By_Example_Where_Clause" />
    </if>
  </update>
  <update id="updateByExample" parameterType="map">
    <!--
      WARNING - @mbggenerated
      This element is automatically generated by MyBatis Generator, do not modify.
      This element was generated on Sat Jan 30 18:31:14 CST 2016.
    -->
    update remark
    set id = #{record.id,jdbcType=BIGINT},
      acc_id = #{record.accId,jdbcType=BIGINT},
      acc_id_obj = #{record.accIdObj,jdbcType=BIGINT},
      clu_id = #{record.cluId,jdbcType=BIGINT},
      remark = #{record.remark,jdbcType=VARCHAR},
      create_dt = #{record.createDt,jdbcType=TIMESTAMP}
    <if test="_parameter != null">
      <include refid="Update_By_Example_Where_Clause" />
    </if>
  </update>
  <update id="updateByPrimaryKeySelective" parameterType="com.uxiaoxi.ym.appserver.db.cluster.dto.Remark">
    <!--
      WARNING - @mbggenerated
      This element is automatically generated by MyBatis Generator, do not modify.
      This element was generated on Sat Jan 30 18:31:14 CST 2016.
    -->
    update remark
    <set>
      <if test="accId != null">
        acc_id = #{accId,jdbcType=BIGINT},
      </if>
      <if test="accIdObj != null">
        acc_id_obj = #{accIdObj,jdbcType=BIGINT},
      </if>
      <if test="cluId != null">
        clu_id = #{cluId,jdbcType=BIGINT},
      </if>
      <if test="remark != null">
        remark = #{remark,jdbcType=VARCHAR},
      </if>
      <if test="createDt != null">
        create_dt = #{createDt,jdbcType=TIMESTAMP},
      </if>
    </set>
    where id = #{id,jdbcType=BIGINT}
  </update>
  <update id="updateByPrimaryKey" parameterType="com.uxiaoxi.ym.appserver.db.cluster.dto.Remark">
    <!--
      WARNING - @mbggenerated
      This element is automatically generated by MyBatis Generator, do not modify.
      This element was generated on Sat Jan 30 18:31:14 CST 2016.
    -->
    update remark
    set acc_id = #{accId,jdbcType=BIGINT},
      acc_id_obj = #{accIdObj,jdbcType=BIGINT},
      clu_id = #{cluId,jdbcType=BIGINT},
      remark = #{remark,jdbcType=VARCHAR},
      create_dt = #{createDt,jdbcType=TIMESTAMP}
    where id = #{id,jdbcType=BIGINT}
  </update>
  <cache>
    <!--
      WARNING - @mbggenerated
      This element is automatically generated by MyBatis Generator, do not modify.
      This element was generated on Sat Jan 30 18:31:14 CST 2016.
    -->
  </cache>
  
        <!-- 自己定义方法 -->
  <select id="selectRemark" parameterType="com.uxiaoxi.ym.appserver.db.cluster.dto.RemarkExample" resultType="java.lang.String">
        SELECT remark
          FROM `remark` 
        <if test="_parameter != null">
          <include refid="Example_Where_Clause" />
        </if>
  </select>
</mapper>